pytextgame/__init__.py
pytextgame/core.py
pytextgame/io.py
pytextgame/actors/__init__.py
pytextgame/actors/chracters.py
pytextgame/actors/items.py
pytextgame/components/__init__.py
pytextgame/components/rooms.py
pytextgame/components/scene.py
pytextgame/graphics/__init__.py
pytextgame/graphics/text.py
PyTextGame-1.0.dist-info/LICENSE
PyTextGame-1.0.dist-info/METADATA
PyTextGame-1.0.dist-info/WHEEL
PyTextGame-1.0.dist-info/top_level.txt
PyTextGame-1.0.dist-info/RECORD
