Metadata-Version: 2.1
Name: PyTextGame
Version: 1.0
Summary: A package for building text based games.
Author-email: Himank Deka <neil.himank3@gmail.com>
Project-URL: Homepage, https://github.com/dev-hd11/pytextgame
Project-URL: Bug Tracker, https://github.com/dev-hd11/pytextgame/issues
Classifier: Programming Language :: Python :: 3.12
Classifier: License :: OSI Approved :: BSD License
Classifier: Operating System :: OS Independent
Requires-Python: >=3.11
License-File: LICENSE
Requires-Dist: keyboard
